MANIFEST.in
README.md
setup.py
KlarnaCheckout.egg-info/PKG-INFO
KlarnaCheckout.egg-info/SOURCES.txt
KlarnaCheckout.egg-info/dependency_links.txt
KlarnaCheckout.egg-info/top_level.txt
klarnacheckout/__init__.py
klarnacheckout/connector.py
klarnacheckout/digest.py
klarnacheckout/order.py
klarnacheckout/recurring.py
klarnacheckout/resource.py
klarnacheckout/useragent.py