Metadata-Version: 1.0
Name: KlarnaCheckout
Version: 3.0.0
Summary: Klarna Checkout library
Home-page: https://developers.klarna.com
Author: Merchant Integration
Author-email: support@klarna.com
License: Apache 2
Platform: UNKNOWN
